{"title":"Từ vựng Tiếng Anh về dụng cụ học tập","vocabulary":[{"en":"pen","example":"I forgot my pen at home.","image":"pen.jpg","pronounce":"(n)","sound":"odnnfdtxvgg2qgz7w3p9qc4bmwcvkggknksb8f9ly.mp3","vi":"bút mực","stt":0},{"en":"pencil","example":"You'd better sharpen your pencil.","image":"pencil.jpg","pronounce":"(n)","sound":"v4cag7sj9xarrdqn5uhz4j39gbswpu3cxj6e9cfdpw.mp3","vi":"bút chì","stt":1},{"en":"paper","example":"She wrote her name and address on a sheet of paper.","image":"paper.jpg","pronounce":"(n)","sound":"z9ti9l69qtd5smszbsftjurxqkb9lpjout3xqwuax4g.mp3","vi":"giấy","stt":2},{"en":"eraser","example":"I buy a pencil and an eraser.","image":"40350.jpg","pronounce":"(n)","sound":"ok9kubsii15wco9akpb6dny1vvfjoc7li8a9wp6xn8.mp3","vi":"Cục tẩy, cục gôm","stt":3},{"en":"pencil sharpener","example":"I've lost my pencil sharpener.","image":"pencil%20sharpener.jpg","pronounce":"(n)","sound":"afafjrrexcwyam0sxlibxt3pibgb6rtwy09h1yrndi.mp3","vi":"đồ gọt bút chì","stt":4},{"en":"book","example":"Have you read any good book recently?","image":"book.jpg","pronounce":"(n)","sound":"n6w0cv4nl5olos6hzz7vm9nqdhl0s7ppf7rxdr3epsc.mp3","vi":"sách","stt":5},{"en":"pack","example":"We passed a group of walkers, carrying huge packs.","image":"backpack.jpg","pronounce":"(n)","sound":"8pkknx0betydlyqbqo3rqcvnmorvwl1lqbrpg4dtfi.mp3","vi":"túi đeo, ba lô","stt":6},{"en":"crayon","example":"He had some crayons.","image":"crayon.jpg","pronounce":"(n)","sound":"dbmmttesstuudws6j3nr5fwlbuhat2ftxpvt25zg6g.mp3","vi":"bút màu sáp","stt":7},{"en":"scissors","example":"Could you pass me the scissors, please?","image":"scissors.jpg","pronounce":"(n)","sound":"9fwjkzls6tnwcqgnv0fekhuveghnlygsgfsig3appo.mp3","vi":"cái kéo","stt":8},{"en":"glue","example":"He sticks to her like glue.","image":"glue.jpg","pronounce":"(n)","sound":"drpztifqpgn1at1ibyucgoh3ynf6kvnt8jojqcli8.mp3","vi":"keo dán","stt":9},{"en":"calculator","example":"My brother needs to buy a pocket calculator to take the exam.","image":"calculator_1.jpg","pronounce":"(n)","sound":"xldwwcwailuifywfamzwb2motlbhwfmuwavbdalzfe.mp3","vi":"máy tính","stt":10},{"en":"compass","example":"I use the compass to draw circle.","image":"compass_1.jpg","pronounce":"(n)","sound":"mtdpfluu3mbo5nunkbqxbjeiwtxfmi5cgrq3wdiejw.mp3","vi":"com-pa","stt":11},{"en":"bag","example":"I left my bag at the shop.","image":"bag_3.jpg","pronounce":"(n)","sound":"is3z5opxgy103r8lefmp2luafhesrfuhuy240gyss.mp3","vi":"cái túi","stt":12},{"en":"ruler","example":"This is my brother's ruler.","image":"ruler.jpg","pronounce":"(n)","sound":"6usimx1zmhuncuif9zqmtvmiuwixnmwqsr8cpyvzs0.mp3","vi":"cây thước","stt":13},{"en":"board","example":"The exam results went up on the board.","image":"board_2.jpg","pronounce":"(n)","sound":"55yq2beoqvdzlac5hyleuj8tillqwjfyyuiliomcwae.mp3","vi":"bảng","stt":14},{"en":"chalk","example":"He picked up a piece of chalk and wrote the answer on the blackboard.","image":"chalk.jpg","pronounce":"(n)","sound":"x24zrq8uzezdoqbfcvafu2fjm4pjxuzme1b4ghssg.mp3","vi":"phấn","stt":15},{"en":"dictionary","example":"To check how a word is spelled, look it up in a dictionary.","image":"dictionary_1.jpg","pronounce":"(n)","sound":"nem5luak2oirsb3txwypuigpo7txpsrvspaq66cwv8.mp3","vi":"từ điển","stt":16},{"en":"watercolour","example":"Most of her paintings were done in watercolours.","image":"watercolour.jpg","pronounce":"(n)","sound":"lrfienhqv7j3gxhnwsevdzdmlmh0ucxvu2uirw4zbk.mp3","vi":"màu nước","stt":17},{"en":"globe","example":"She used this globe to teach.","image":"globe.jpg","pronounce":"(n)","sound":"tlq0xysfxpw90etbcvqq1a0qyn1uagr47wghal2mww.mp3","vi":"quả địa cầu","stt":18},{"en":"protractor","example":"You must prepare protractor and compass before you start.","image":"protractor.jpg","pronounce":"(n)","sound":"sttrlgejtkpn8bruxzu70wdkprjlern6yh4ehbqysk.mp3","vi":"thước đo góc","stt":19},{"en":"stapler","example":"This stapler is broken.","image":"stapler.jpg","pronounce":"(n)","sound":"4isml9hxeqhcuwxwdhrpbej3ub6znokoczzqf4l2k.mp3","vi":"dụng cụ kim bấm","stt":20},{"en":"paintbrush","example":"He has bought a new paintbrush.","image":"paintbrush.jpg","pronounce":"(n)","sound":"3rw5p1otxmw1nuod3eoexjwxwwfilsjmnwcxrkcb6c.mp3","vi":"cọ quét sơn","stt":21}]}