{"title":"Từ vựng tiếng Anh về Môi trường","vocabulary":[{"en":"land","example":"What should we do with such wide area of land?","image":"land_1.jpg","pronounce":"(n)","sound":"s7ejon0xapzb4lqhwfingdjilgcahomiwvywspw22e.mp3","vi":"đất, vùng đất","stt":0},{"en":"pollute","example":"The pesticides used on many farms are polluting the water supply .","image":"pollute.jpg","pronounce":"(v)","sound":"hy9umpwrf6v5ndojpoiljavhybqhdcdiao2gyt4hc.mp3","vi":"gây ô nhiễm","stt":1},{"en":"decompose","example":"The body must have been decomposing for several weeks.","image":"decompose.jpg","pronounce":"(v)","sound":"rzpwdh4vm5mvxysno4wkihc35d5vc6dgqyj7p5xda.mp3","vi":"phân hủy","stt":2},{"en":"balance","example":"We need to have a good balance between job and life.","image":"balance_1.jpg","pronounce":"(n)","sound":"t486phoot7cj9ub5vncmdi5o0n95xehzbdouac17p8.mp3","vi":"sự cân bằng","stt":3},{"en":"climate change","example":"Climate change makes the Earth hotter.","image":"climate%20change.jpg","pronounce":"(n)","sound":"nlsqfgkanxbljpkhalxfqqnxjbtsjay7zguwftagk.mp3","vi":"thay đổi khí hậu","stt":4},{"en":"global warming","example":"Nowadays, iceberg is a victim of the global warming.","image":"global%20warming.jpg","pronounce":"(n)","sound":"fbjuq98drjnxsecfl19t5vex98dzufb8nbhypitxui.mp3","vi":"sự ấm lên toàn cầu","stt":5},{"en":"oil slick","example":"The accident left a large oil slick on the sea.","image":"oil%20slick.jpg","pronounce":"(n)","sound":"gl5v6oymp5zegnmspbxncga0ges7eieprx3kcnply.mp3","vi":"vết dầu loang","stt":6},{"en":"ozone layer","example":"Our ozone layer is destroyed by air pollution.","image":"ozone%20layer.jpg","pronounce":"(n)","sound":"qisgws3uptmu4ta42gwcam5cygcdwohpivqwu917e.mp3","vi":"tầng ozon","stt":7},{"en":"biodiversity","example":"Vietnam has been recognized as a nation with high biodiversity.","image":"biodiversity_2.jpg","pronounce":"(n)","sound":"qowzwmmw8vjuxdrosyaialzlqz7j4o4w5ozvbteko.mp3","vi":"đa dạng sinh học","stt":8},{"en":"ecology","example":"The oil spill caused terrible damage to the fragile ecology of the coast.","image":"ecology.jpg","pronounce":"(n)","sound":"8wyeknd9cxmvgazwyqvyqy6uew56x8lxyktgtimm4.mp3","vi":"sinh thái học","stt":9},{"en":"water","example":"Water has accounted 3/4 of surface of the Earth.","image":"water_1.jpg","pronounce":"(n)","sound":"qte0n2mmggxd77owvuhmorj6pp7u2queabasii4hyu.mp3","vi":"nước","stt":10},{"en":"air","example":"The higher, the washier air is.","image":"air.jpg","pronounce":"(n)","sound":"84emewl5bxibvvo8tfza8pjhd77lyb6h9p8lxnjgdw.mp3","vi":"không khí","stt":11},{"en":"forest","example":"The children got lost in the forest.","image":"forest%20%281%29.jpg","pronounce":"(n)","sound":"dyqdshudsuetxrkb1645h3hdsilkf6dgpytnuimsqzq.mp3","vi":"rừng","stt":12},{"en":"flora","example":"As tourism is more developed, people worry about the damage to the flora and fauna of the island.","image":"flora_2.jpg","pronounce":"(n)","sound":"fkzpgqimkkouihoolof5xkoaj9mo7ki2gs7w9gj3dnk.mp3","vi":"hệ thực vật","stt":13},{"en":"creature","example":"Rainforests are filled with amazing creatures.","image":"creature.jpg","pronounce":"(n)","sound":"55mfh567mdpz32pedkbzi63rsedahm6penbgbr0fc.mp3","vi":"sinh vật, loài vật","stt":14},{"en":"insect","example":"Ants, beetles, butterflies, and flies are all insects.","image":"insect.jpg","pronounce":"(n)","sound":"migwrpcbjyq89avllyj0dnk5fb370mgifp3xbbrasg.mp3","vi":"côn trùng","stt":15},{"en":"reproduction","example":"We are researching reproduction in elephants.","image":"reproduction.jpg","pronounce":"(n)","sound":"mprjgpqdqduaqipot6axio45p1pp1ju9xrx7rqbd4.mp3","vi":"sự sinh sản","stt":16},{"en":"wildlife","example":"Wildlife deserves to receive the protection from human.","image":"wildlife.jpg","pronounce":"(n)","sound":"qgtxtikbco79kr2q2eriowtvlokuc6fwltp5aerkhm.mp3","vi":"động vật hoang dã","stt":17},{"en":"sewage","example":"Industrial sewage continues to contaminate their beaches.","image":"sewage_1.jpg","pronounce":"(n)","sound":"aravcsymjyhodwygyl6wmggmtajeve4qpooe8dze.mp3","vi":"nước thải","stt":18}]}